myf_face_recognition
